jason_json/__init__.py
jason_json/main.py
jason_json/model_types.py
jason_json/py.typed
jason_json/utils.py
jason_json-1.1.0.dist-info/METADATA
jason_json-1.1.0.dist-info/WHEEL
jason_json-1.1.0.dist-info/entry_points.txt
jason_json-1.1.0.dist-info/licenses/LICENSE
jason_json-1.1.0.dist-info/RECORD
