Metadata-Version: 2.4
Name: jason-json
Version: 1.1.0
Summary: Jason (https://jason.co.jp) JSON Builder
Project-URL: repository, https://github.com/eggplants/jason-json
Author-email: eggplants <w10776e8w@yahoo.co.jp>
License: MIT
License-File: LICENSE
Keywords: japanese,jason,json,scraping
Classifier: Development Status :: 3 - Alpha
Classifier: License :: OSI Approved :: MIT License
Classifier: Programming Language :: Python :: 3 :: Only
Classifier: Programming Language :: Python :: 3.10
Classifier: Programming Language :: Python :: 3.11
Classifier: Programming Language :: Python :: 3.12
Classifier: Programming Language :: Python :: 3.13
Classifier: Programming Language :: Python :: 3.14
Classifier: Typing :: Typed
Requires-Python: <4,>=3.10
Requires-Dist: beautifulsoup4<5,>=4.12.3
Requires-Dist: lxml<7,>=5.3
Requires-Dist: typed-argument-parser<2,>=1.10.1
Requires-Dist: types-beautifulsoup4<5,>=4.12.0.20241020
